{
  "ssh.title": "Connexions SSH",
  "ssh.subtitle": "Gérez vos serveurs et connexions SSH",
  "ssh.addServer": "Ajouter un serveur",
  "ssh.editServer": "Modifier le serveur",
  "ssh.deleteServer": "Supprimer le serveur",
  "ssh.serverName": "Nom du serveur",
  "ssh.host": "Hôte",
  "ssh.port": "Port",
  "ssh.username": "Nom d'utilisateur",
  "ssh.password": "Mot de passe",
  "ssh.privateKey": "Clé privée",
  "ssh.connect": "(fr) Connect",
  "ssh.disconnect": "Déconnecter",
  "ssh.connecting": "(fr) Connecting to SSH",
  "ssh.connected": "Connecté",
  "ssh.connectionFailed": "Échec de la connexion",
  "ssh.enterPassword": "Entrer le mot de passe",
  "ssh.noServers": "Aucun serveur SSH configuré",
  "ssh.addFirstServer": "Ajoutez votre premier serveur pour commencer",
  "ssh.settings.title": "(fr) SSH Connections",
  "ssh.import.hint": "(fr) Import from ~/.ssh/config",
  "ssh.group.add": "(fr) Add Group",
  "ssh.conn.add": "(fr) Add Connection",
  "ssh.none": "(fr) No SSH Connections",
  "ssh.import.success": "(fr) Imported {} connection(s) from ~/.ssh/config",
  "ssh.editor.modified": "(fr) Modified",
  "ssh.editor.loading": "(fr) Loading file...",
  "ssh.editor.error": "(fr) Error loading file",
  "ssh.editor.saved": "(fr) Saved successfully",
  "ssh.settings.subtitle": "(fr) Manage remote server connections and credentials",
  "ssh.uploading": "(fr) Uploading: {}",
  "ssh.password.title": "(fr) SSH Password Required",
  "ssh.password.hint": "(fr) Enter password for {}",
  "ssh.password.label": "(fr) Password",
  "ssh.password.keychain": "(fr) Password will be saved to Keychain",
  "ssh.auth.agent": "(fr) Will use SSH Agent for authentication",
  "ssh.editor.conn": "(fr) Connection",
  "ssh.editor.auth": "(fr) Authentication",
  "ssh.editor.appearance": "(fr) Appearance",
  "ssh.editor.notes": "(fr) Notes",
  "ssh.editor.none": "(fr) None",
  "ssh.badge": "(fr) SSH"
}